tegem_tools/__init__.py
tegem_tools/Mixin/__init__.py
tegem_tools/Mixin/mixins.py
tegem_tools/feedParsers/__init__.py
tegem_tools/feedParsers/baseParser.py
tegem_tools/feedParsers/descriptionParser.py
tegem_tools/feedParsers/imageParser.py
tegem_tools/feedParsers/titleParser.py
tegem_tools/logger/__init__.py
tegem_tools/logger/log.py
tegem_tools-0.0.8.dist-info/LICENSE
tegem_tools-0.0.8.dist-info/METADATA
tegem_tools-0.0.8.dist-info/WHEEL
tegem_tools-0.0.8.dist-info/top_level.txt
tegem_tools-0.0.8.dist-info/RECORD
