Metadata-Version: 2.1
Name: tegem_tools
Version: 0.0.8
Summary: package for tegem project
Author: alexmais95
Author-email: alexlove9596@gmail.com
License-File: LICENSE
Requires-Dist: aiohttp==3.10.5
Requires-Dist: beautifulsoup4==4.12.3
Requires-Dist: feedparser==6.0.11
Requires-Dist: lxml==5.3.0
Requires-Dist: playwright==1.47.0
Requires-Dist: requests==2.32.2
Requires-Dist: requests-ip-rotator==1.0.14
Requires-Dist: deep-translator==1.11.4
Requires-Dist: sentry-sdk==2.19.0
Requires-Dist: colorama==0.4.6
Requires-Dist: fake-useragent==2.2.0
